MANIFEST.in
README
ini.py
setup.py
tests.py
INI.egg-info/PKG-INFO
INI.egg-info/SOURCES.txt
INI.egg-info/dependency_links.txt
INI.egg-info/top_level.txt
docs/Makefile
docs/conf.py
docs/index.rst
docs/make.bat