Metadata-Version: 1.0
Name: INI
Version: 0.1
Summary: Simple json/pickle like ini-file parsing.
Home-page: http://packages.python.org/INI/
Author: Daniel Neuhäuser
Author-email: dasdasich@gmail.com
License: MIT
Platform: UNKNOWN
